flake8_class_constants.py
flake8_class_constants-0.1.2.dist-info/LICENSE
flake8_class_constants-0.1.2.dist-info/METADATA
flake8_class_constants-0.1.2.dist-info/WHEEL
flake8_class_constants-0.1.2.dist-info/entry_points.txt
flake8_class_constants-0.1.2.dist-info/top_level.txt
flake8_class_constants-0.1.2.dist-info/RECORD
